hw/hw5/E15Process.v
module E15Process(input clk);

   // Execution stages
   parameter 
      fetch=2'd0, 
      decode=2'd1, 
      exec=2'd2, 
      store=2'd3;

   // Register names
   parameter 
      Rg0 = 2'b00, Rg1 = 2'b01,
      Rg2 = 2'b10, Rg3 = 2'b11, 
      RXX = 2'b00;

   // Opcodes
   parameter
     jmp  = 4'b0000, jz   = 4'b0010,
     movi = 4'b1001, mov  = 4'b1000,
     addi = 4'b1011, add  = 4'b1010,
     subi = 4'b1101, sub  = 4'b1100,
     cmpi = 4'b1111, cmp  = 4'b1110,
     jnz  = 4'b0011;
   
   // Bus signals
   parameter   
     bEn_R0 = 3'd0, bEn_R1 = 3'd1, 
     bEn_R2 = 3'd2, bEn_R3 = 3'd3, 
     bEn_ALU = 3'd4, bEn_Imm = 3'd5;

   reg [3:0] pc;              // Program Counter
   reg [3:0] r0, r1, r2, r3;  // Registers

   wire [3:0] mBus, dstBus;    // Buses
   reg [3:0] opCode;          // op code
   reg [1:0] src, dst;        // src and dst register
   reg [3:0] immData;         // "Immediate" data


   reg  [3:0] pcIncr; // Program Counter Increment
   wire [3:0] pcRes;  // Output of pc ALU
   wire       pcz;    // Unused - zero flag for pc ALU
   
   reg [1:0]  myState;      // State (phase of excution)
   reg [11:0] myROM [15:0]; // ROM (holds program)
   reg [3:0]  mbEn, dbEn;   // Used to determine which values are passed
                            // on the two buses

   reg        addNotSub; // Determines if ALU adds or subtracts
   reg [3:0]  aluOut;    // Register to hold output of main ALU
   reg        zFlag;     // Zero flag
   wire [3:0] resVal;    // Output (combinational) of ALU
   wire       zVal;      // Output (combinational) of ALU zero flag

   initial
     begin

        `include "loop.v"
        
        pc = 4'b0000;
        myState = fetch;
        
     end
   
   always @(posedge clk)

     case(myState)
       // Fetch phase:
       //    Save instruction to registers.
       //    Move to next phase.
       fetch:
         begin
            {opCode, src, dst, immData} = myROM[pc];
            myState <= decode;
         end

       // Decode phase:
       //    Send concrete values to ALU by setting
       //    mbEn and dbEn to to read the appropriate
       //    values (registers or immediates).
       //    Set addNotSub appropriately for arithmetic.
       //    Move to next phase.
       decode:
         begin
            // TODO: set mbEn, dbEn, addNotSub, and myState
            //       based on opCode

            addNotSub <= ((opCode == add) | (opCode == addi));
            case (opCode)
              add, sub, cmp, mov:
              begin
                case (src)
                  Rg0: mbEn <= bEn_R0;
                  Rg1: mbEn <= bEn_R1;
                  Rg2: mbEn <= bEn_R2;
                  Rg3: mbEn <= bEn_R3;
                endcase
                case (dst)
                  Rg0: dbEn <= bEn_R0;
                  Rg1: dbEn <= bEn_R1;
                  Rg2: dbEn <= bEn_R2;
                  Rg3: dbEn <= bEn_R3;
                endcase
              end
              jmp, jz, jnz:
              begin
                mbEn <= bEn_Imm;
              end
              movi, addi, subi, cmpi:
              begin
                mbEn <= bEn_Imm;
                case (dst)
                  Rg0: dbEn <= bEn_R0;
                  Rg1: dbEn <= bEn_R1;
                  Rg2: dbEn <= bEn_R2;
                  Rg3: dbEn <= bEn_R3;
                endcase
              end
            endcase
            myState <= exec;
         end
       
       // Exec phase:
       //    Read result from ALU, for instructions that
       //    use it:
       //       Set mbEn to select results from ALU.
       //       Set aluOut to ALU numeric output.
       //       Set zFlag to ALU zero flag output.
       //    Set pcIncr to the relative address of
       //    the next instruction, depending on the
       //    opcode.
       //    Move to next phase.
       exec:
         begin
            case(opCode)
              addi, add, subi, sub, cmpi, cmp:
                begin
                   mbEn <= bEn_ALU;
                   aluOut <= resVal;
                   zFlag <= zVal;
                end
            endcase
            // TODO: set pcIncr

            pcIncr <= (opCode == jmp) ? immData :
                   (opCode == jz && zFlag) ? immData :
                   (opCode == jnz && !zFlag) ? immData : 4'b0001;

            myState <= store;
         end
       
       // Store phase:
       //    Write registers, if appropriate.
       //    Increment pc and move to first phase.
       store:
         begin
            // TODO: store value from mBus into register, if appropriate
            case (opCode)
                add, addi, sub, subi, mov, movi:
                case (dst)
                  Rg0: r0 <= mBus;
                  Rg1: r1 <= mBus;
                  Rg2: r2 <= mBus;
                  Rg3: r3 <= mBus;
                endcase
            endcase
            pc <= pcRes;
            myState <= fetch;
         end
       
     endcase
   
   assign mBus = (mbEn==bEn_R0)  ? r0      : 
                 (mbEn==bEn_R1)  ? r1      : 
                 (mbEn==bEn_R2)  ? r2      : 
                 (mbEn==bEn_R3)  ? r3      : 
                 (mbEn==bEn_Imm) ? immData : 
                 (mbEn==bEn_ALU) ? aluOut  : 0 ;

   assign dstBus = (dbEn==bEn_R0)  ? r0 :
                   (dbEn==bEn_R1)  ? r1 :
                   (dbEn==bEn_R2)  ? r2 :
                   (dbEn==bEn_R3)  ? r3 : 0;

   simpleALU dataALU(addNotSub, mBus, dstBus, zVal, resVal);
   simpleALU pcALU(1'b1, pc, pcIncr, pcz, pcRes);
endmodule


module simpleALU(
    input addNotSub,
    input [3:0] src, dst,
    output zFlag,
    output [3:0] res);
    assign res = addNotSub ? dst + src : dst - src;
    assign zFlag = !(res);
endmodule


//ra0Eequ6ucie6Jei0koh6phishohm9

hw/hw3/E15Process_tb.v
`timescale 1ns/100ps
`default_nettype none
`include "E15Process.v"

module E15Process_TB;

   reg clk = 0;


   E15Process proc(clk);

   always #3
     clk = ~clk;

   initial begin
      $dumpfile("E15Process_tb.vcd");
      $dumpvars(0, E15Process_TB);
      #1000

      $display("Final state of register file:\n\tr0=%d\n\tr1=%d\n\tr2=%d\n\tr3=%d", 
       proc.r0, proc.r1, proc.r2, proc.r3);

      $finish;
   end

endmodule // E15Process_TB

hw/hw5/E15Process_tb.vcd
$date
	Wed Mar 22 23:08:54 2023
$end
$version
	Icarus Verilog
$end
$timescale
	100ps
$end
$scope module E15Process_TB $end
$var reg 1 ! clk $end
$scope module proc $end
$var wire 1 ! clk $end
$var wire 1 " zVal $end
$var wire 4 # resVal [3:0] $end
$var wire 1 $ pcz $end
$var wire 4 % pcRes [3:0] $end
$var wire 4 & mBus [3:0] $end
$var wire 4 ' dstBus [3:0] $end
$var reg 1 ( addNotSub $end
$var reg 4 ) aluOut [3:0] $end
$var reg 4 * dbEn [3:0] $end
$var reg 2 + dst [1:0] $end
$var reg 4 , immData [3:0] $end
$var reg 4 - mbEn [3:0] $end
$var reg 2 . myState [1:0] $end
$var reg 4 / opCode [3:0] $end
$var reg 4 0 pc [3:0] $end
$var reg 4 1 pcIncr [3:0] $end
$var reg 4 2 r0 [3:0] $end
$var reg 4 3 r1 [3:0] $end
$var reg 4 4 r2 [3:0] $end
$var reg 4 5 r3 [3:0] $end
$var reg 2 6 src [1:0] $end
$var reg 1 7 zFlag $end
$scope module dataALU $end
$var wire 1 ( addNotSub $end
$var wire 4 8 dst [3:0] $end
$var wire 4 9 src [3:0] $end
$var wire 1 " zFlag $end
$var wire 4 : res [3:0] $end
$upscope $end
$scope module pcALU $end
$var wire 1 ; addNotSub $end
$var wire 4 < dst [3:0] $end
$var wire 4 = res [3:0] $end
$var wire 4 > src [3:0] $end
$var wire 1 $ zFlag $end
$upscope $end
$upscope $end
$upscope $end
$enddefinitions $end
#0
$dumpvars
b0 >
bx =
bx <
1;
bx :
bx 9
bx 8
x7
bx 6
bx 5
bx 4
bx 3
bx 2
bx 1
b0 0
bx /
b0 .
bx -
bx ,
bx +
bx *
bx )
x(
bx '
bx &
bx %
x$
bx #
x"
0!
$end
#10
b1 .
b1001 /
b0 6
b10 +
b0 ,
1!
#20
0!
#30
b0 &
b0 9
b10 .
b10 *
b101 -
0(
1!
#40
0!
#50
b11 .
0$
b1 %
b1 =
b1 1
b1 <
1!
#60
0!
#70
1"
b0 #
b0 :
b0 '
b0 8
b0 .
b10 %
b10 =
b1 0
b1 >
b0 4
1!
#80
0!
#90
b1 .
0"
b1111 #
b1111 :
b1 &
b1 9
b1 +
b1 ,
1!
#100
0!
#110
x"
bx #
bx :
bx '
bx 8
b10 .
b1 *
1!
#120
0!
#130
b11 .
1!
#140
0!
#150
1"
b0 #
b0 :
b1 '
b1 8
b0 .
b11 %
b11 =
b10 0
b10 >
b1 3
1!
#160
0!
#170
b1 .
0"
b1 #
b1 :
b0 &
b0 9
b1010 /
b1 6
b10 +
b0 ,
1!
#180
0!
#190
b0 '
b0 8
b1 &
b1 9
b10 .
b10 *
b1 -
1(
1!
#200
0!
#210
0"
b1 #
b1 :
b1 &
b1 9
b11 .
07
b1 )
b100 -
1!
#220
0!
#230
b10 #
b10 :
b1 '
b1 8
b0 .
b100 %
b100 =
b11 0
b11 >
b1 4
1!
#240
0!
#250
b1 .
b1111 /
b0 6
b111 ,
1!
#260
0!
#270
b111 &
b111 9
0"
b1010 #
b1010 :
b10 .
b101 -
0(
1!
#280
0!
#290
b111 #
b111 :
b1010 &
b1010 9
b11 .
b1010 )
b100 -
1!
#300
0!
#310
b0 .
b101 %
b101 =
b100 0
b100 >
1!
#320
0!
#330
b1 .
b11 /
b0 +
b1110 ,
1!
#340
0!
#350
b11 #
b11 :
b1110 &
b1110 9
b10 .
b101 -
1!
#360
0!
#370
b11 .
b10 %
b10 =
b1110 1
b1110 <
1!
#380
0!
#390
b0 .
1$
b0 %
b0 =
b10 0
b10 >
1!
#400
0!
#410
b1 .
b1 #
b1 :
b0 &
b0 9
b1010 /
b1 6
b10 +
b0 ,
1!
#420
0!
#430
b10 #
b10 :
b1 &
b1 9
b10 .
b1 -
1(
1!
#440
0!
#450
b11 #
b11 :
b10 &
b10 9
b11 .
0$
b11 %
b11 =
b1 1
b1 <
b10 )
b100 -
1!
#460
0!
#470
b100 #
b100 :
b10 '
b10 8
b0 .
b100 %
b100 =
b11 0
b11 >
b10 4
1!
#480
0!
#490
b1 .
b1111 /
b0 6
b111 ,
1!
#500
0!
#510
b111 &
b111 9
0"
b1011 #
b1011 :
b10 .
b101 -
0(
1!
#520
0!
#530
b111 #
b111 :
b1011 &
b1011 9
b11 .
b1011 )
b100 -
1!
#540
0!
#550
b0 .
b101 %
b101 =
b100 0
b100 >
1!
#560
0!
#570
b1 .
b11 /
b0 +
b1110 ,
1!
#580
0!
#590
b100 #
b100 :
b1110 &
b1110 9
b10 .
b101 -
1!
#600
0!
#610
b11 .
b10 %
b10 =
b1110 1
b1110 <
1!
#620
0!
#630
b0 .
1$
b0 %
b0 =
b10 0
b10 >
1!
#640
0!
#650
b1 .
b10 #
b10 :
b0 &
b0 9
b1010 /
b1 6
b10 +
b0 ,
1!
#660
0!
#670
b11 #
b11 :
b1 &
b1 9
b10 .
b1 -
1(
1!
#680
0!
#690
b101 #
b101 :
b11 &
b11 9
b11 .
0$
b11 %
b11 =
b1 1
b1 <
b11 )
b100 -
1!
#700
0!
#710
b110 #
b110 :
b11 '
b11 8
b0 .
b100 %
b100 =
b11 0
b11 >
b11 4
1!
#720
0!
#730
b1 .
b1111 /
b0 6
b111 ,
1!
#740
0!
#750
b111 &
b111 9
0"
b1100 #
b1100 :
b10 .
b101 -
0(
1!
#760
0!
#770
b111 #
b111 :
b1100 &
b1100 9
b11 .
b1100 )
b100 -
1!
#780
0!
#790
b0 .
b101 %
b101 =
b100 0
b100 >
1!
#800
0!
#810
b1 .
b11 /
b0 +
b1110 ,
1!
#820
0!
#830
b101 #
b101 :
b1110 &
b1110 9
b10 .
b101 -
1!
#840
0!
#850
b11 .
b10 %
b10 =
b1110 1
b1110 <
1!
#860
0!
#870
b0 .
1$
b0 %
b0 =
b10 0
b10 >
1!
#880
0!
#890
b1 .
b11 #
b11 :
b0 &
b0 9
b1010 /
b1 6
b10 +
b0 ,
1!
#900
0!
#910
b100 #
b100 :
b1 &
b1 9
b10 .
b1 -
1(
1!
#920
0!
#930
b111 #
b111 :
b100 &
b100 9
b11 .
0$
b11 %
b11 =
b1 1
b1 <
b100 )
b100 -
1!
#940
0!
#950
b1000 #
b1000 :
b100 '
b100 8
b0 .
b100 %
b100 =
b11 0
b11 >
b100 4
1!
#960
0!
#970
b1 .
b1111 /
b0 6
b111 ,
1!
#980
0!
#990
b111 &
b111 9
0"
b1101 #
b1101 :
b10 .
b101 -
0(
1!
#1000
0!
#1010
b111 #
b111 :
b1101 &
b1101 9
b11 .
b1101 )
b100 -
1!
#1020
0!
#1030
b0 .
b101 %
b101 =
b100 0
b100 >
1!
#1040
0!
#1050
b1 .
b11 /
b0 +
b1110 ,
1!
#1060
0!
#1070
b110 #
b110 :
b1110 &
b1110 9
b10 .
b101 -
1!
#1080
0!
#1090
b11 .
b10 %
b10 =
b1110 1
b1110 <
1!
#1100
0!
#1110
b0 .
1$
b0 %
b0 =
b10 0
b10 >
1!
#1120
0!
#1130
b1 .
b100 #
b100 :
b0 &
b0 9
b1010 /
b1 6
b10 +
b0 ,
1!
#1140
0!
#1150
b101 #
b101 :
b1 &
b1 9
b10 .
b1 -
1(
1!
#1160
0!
#1170
b1001 #
b1001 :
b101 &
b101 9
b11 .
0$
b11 %
b11 =
b1 1
b1 <
b101 )
b100 -
1!
#1180
0!
#1190
b1010 #
b1010 :
b101 '
b101 8
b0 .
b100 %
b100 =
b11 0
b11 >
b101 4
1!
#1200
0!
#1210
b1 .
b1111 /
b0 6
b111 ,
1!
#1220
0!
#1230
b111 &
b111 9
0"
b1110 #
b1110 :
b10 .
b101 -
0(
1!
#1240
0!
#1250
b111 #
b111 :
b1110 &
b1110 9
b11 .
b1110 )
b100 -
1!
#1260
0!
#1270
b0 .
b101 %
b101 =
b100 0
b100 >
1!
#1280
0!
#1290
b1 .
b11 /
b0 +
b1110 ,
1!
#1300
0!
#1310
b10 .
b101 -
1!
#1320
0!
#1330
b11 .
b10 %
b10 =
b1110 1
b1110 <
1!
#1340
0!
#1350
b0 .
1$
b0 %
b0 =
b10 0
b10 >
1!
#1360
0!
#1370
b1 .
b101 #
b101 :
b0 &
b0 9
b1010 /
b1 6
b10 +
b0 ,
1!
#1380
0!
#1390
b110 #
b110 :
b1 &
b1 9
b10 .
b1 -
1(
1!
#1400
0!
#1410
b1011 #
b1011 :
b110 &
b110 9
b11 .
0$
b11 %
b11 =
b1 1
b1 <
b110 )
b100 -
1!
#1420
0!
#1430
b1100 #
b1100 :
b110 '
b110 8
b0 .
b100 %
b100 =
b11 0
b11 >
b110 4
1!
#1440
0!
#1450
b1 .
b1111 /
b0 6
b111 ,
1!
#1460
0!
#1470
b111 &
b111 9
0"
b1111 #
b1111 :
b10 .
b101 -
0(
1!
#1480
0!
#1490
b111 #
b111 :
b1111 &
b1111 9
b11 .
b1111 )
b100 -
1!
#1500
0!
#1510
b0 .
b101 %
b101 =
b100 0
b100 >
1!
#1520
0!
#1530
b1 .
b11 /
b0 +
b1110 ,
1!
#1540
0!
#1550
b1000 #
b1000 :
b1110 &
b1110 9
b10 .
b101 -
1!
#1560
0!
#1570
b11 .
b10 %
b10 =
b1110 1
b1110 <
1!
#1580
0!
#1590
b0 .
1$
b0 %
b0 =
b10 0
b10 >
1!
#1600
0!
#1610
b1 .
b110 #
b110 :
b0 &
b0 9
b1010 /
b1 6
b10 +
b0 ,
1!
#1620
0!
#1630
b111 #
b111 :
b1 &
b1 9
b10 .
b1 -
1(
1!
#1640
0!
#1650
b1101 #
b1101 :
b111 &
b111 9
b11 .
0$
b11 %
b11 =
b1 1
b1 <
b111 )
b100 -
1!
#1660
0!
#1670
b1110 #
b1110 :
b111 '
b111 8
b0 .
b100 %
b100 =
b11 0
b11 >
b111 4
1!
#1680
0!
#1690
b1 .
b1111 /
b0 6
b111 ,
1!
#1700
0!
#1710
1"
b0 #
b0 :
b10 .
b101 -
0(
1!
#1720
0!
#1730
0"
b111 #
b111 :
b0 &
b0 9
b11 .
17
b0 )
b100 -
1!
#1740
0!
#1750
b0 .
b101 %
b101 =
b100 0
b100 >
1!
#1760
0!
#1770
b1 .
b11 /
b0 +
b1110 ,
1!
#1780
0!
#1790
b1001 #
b1001 :
b1110 &
b1110 9
b10 .
b101 -
1!
#1800
0!
#1810
b11 .
1!
#1820
0!
#1830
b0 .
b110 %
b110 =
b101 0
b101 >
1!
#1840
0!
#1850
b1 .
b111 #
b111 :
b0 &
b0 9
b0 /
b0 ,
1!
#1860
0!
#1870
b10 .
1!
#1880
0!
#1890
b11 .
b101 %
b101 =
b0 1
b0 <
1!
#1900
0!
#1910
b0 .
1!
#1920
0!
#1930
b1 .
1!
#1940
0!
#1950
b10 .
1!
#1960
0!
#1970
b11 .
1!
#1980
0!
#1990
b0 .
1!
#2000
0!
#2010
b1 .
1!
#2020
0!
#2030
b10 .
1!
#2040
0!
#2050
b11 .
1!
#2060
0!
#2070
b0 .
1!
#2080
0!
#2090
b1 .
1!
#2100
0!
#2110
b10 .
1!
#2120
0!
#2130
b11 .
1!
#2140
0!
#2150
b0 .
1!
#2160
0!
#2170
b1 .
1!
#2180
0!
#2190
b10 .
1!
#2200
0!
#2210
b11 .
1!
#2220
0!
#2230
b0 .
1!
#2240
0!
#2250
b1 .
1!
#2260
0!
#2270
b10 .
1!
#2280
0!
#2290
b11 .
1!
#2300
0!
#2310
b0 .
1!
#2320
0!
#2330
b1 .
1!
#2340
0!
#2350
b10 .
1!
#2360
0!
#2370
b11 .
1!
#2380
0!
#2390
b0 .
1!
#2400
0!
#2410
b1 .
1!
#2420
0!
#2430
b10 .
1!
#2440
0!
#2450
b11 .
1!
#2460
0!
#2470
b0 .
1!
#2480
0!
#2490
b1 .
1!
#2500
0!
#2510
b10 .
1!
#2520
0!
#2530
b11 .
1!
#2540
0!
#2550
b0 .
1!
#2560
0!
#2570
b1 .
1!
#2580
0!
#2590
b10 .
1!
#2600
0!
#2610
b11 .
1!
#2620
0!
#2630
b0 .
1!
#2640
0!
#2650
b1 .
1!
#2660
0!
#2670
b10 .
1!
#2680
0!
#2690
b11 .
1!
#2700
0!
#2710
b0 .
1!
#2720
0!
#2730
b1 .
1!
#2740
0!
#2750
b10 .
1!
#2760
0!
#2770
b11 .
1!
#2780
0!
#2790
b0 .
1!
#2800
0!
#2810
b1 .
1!
#2820
0!
#2830
b10 .
1!
#2840
0!
#2850
b11 .
1!
#2860
0!
#2870
b0 .
1!
#2880
0!
#2890
b1 .
1!
#2900
0!
#2910
b10 .
1!
#2920
0!
#2930
b11 .
1!
#2940
0!
#2950
b0 .
1!
#2960
0!
#2970
b1 .
1!
#2980
0!
#2990
b10 .
1!
#3000
0!
#3010
b11 .
1!
#3020
0!
#3030
b0 .
1!
#3040
0!
#3050
b1 .
1!
#3060
0!
#3070
b10 .
1!
#3080
0!
#3090
b11 .
1!
#3100
0!
#3110
b0 .
1!
#3120
0!
#3130
b1 .
1!
#3140
0!
#3150
b10 .
1!
#3160
0!
#3170
b11 .
1!
#3180
0!
#3190
b0 .
1!
#3200
0!
#3210
b1 .
1!
#3220
0!
#3230
b10 .
1!
#3240
0!
#3250
b11 .
1!
#3260
0!
#3270
b0 .
1!
#3280
0!
#3290
b1 .
1!
#3300
0!
#3310
b10 .
1!
#3320
0!
#3330
b11 .
1!
#3340
0!
#3350
b0 .
1!
#3360
0!
#3370
b1 .
1!
#3380
0!
#3390
b10 .
1!
#3400
0!
#3410
b11 .
1!
#3420
0!
#3430
b0 .
1!
#3440
0!
#3450
b1 .
1!
#3460
0!
#3470
b10 .
1!
#3480
0!
#3490
b11 .
1!
#3500
0!
#3510
b0 .
1!
#3520
0!
#3530
b1 .
1!
#3540
0!
#3550
b10 .
1!
#3560
0!
#3570
b11 .
1!
#3580
0!
#3590
b0 .
1!
#3600
0!
#3610
b1 .
1!
#3620
0!
#3630
b10 .
1!
#3640
0!
#3650
b11 .
1!
#3660
0!
#3670
b0 .
1!
#3680
0!
#3690
b1 .
1!
#3700
0!
#3710
b10 .
1!
#3720
0!
#3730
b11 .
1!
#3740
0!
#3750
b0 .
1!
#3760
0!
#3770
b1 .
1!
#3780
0!
#3790
b10 .
1!
#3800
0!
#3810
b11 .
1!
#3820
0!
#3830
b0 .
1!
#3840
0!
#3850
b1 .
1!
#3860
0!
#3870
b10 .
1!
#3880
0!
#3890
b11 .
1!
#3900
0!
#3910
b0 .
1!
#3920
0!
#3930
b1 .
1!
#3940
0!
#3950
b10 .
1!
#3960
0!
#3970
b11 .
1!
#3980
0!
#3990
b0 .
1!
#4000
0!
#4010
b1 .
1!
#4020
0!
#4030
b10 .
1!
#4040
0!
#4050
b11 .
1!
#4060
0!
#4070
b0 .
1!
#4080
0!
#4090
b1 .
1!
#4100
0!
#4110
b10 .
1!
#4120
0!
#4130
b11 .
1!
#4140
0!
#4150
b0 .
1!
#4160
0!
#4170
b1 .
1!
#4180
0!
#4190
b10 .
1!
#4200
0!
#4210
b11 .
1!
#4220
0!
#4230
b0 .
1!
#4240
0!
#4250
b1 .
1!
#4260
0!
#4270
b10 .
1!
#4280
0!
#4290
b11 .
1!
#4300
0!
#4310
b0 .
1!
#4320
0!
#4330
b1 .
1!
#4340
0!
#4350
b10 .
1!
#4360
0!
#4370
b11 .
1!
#4380
0!
#4390
b0 .
1!
#4400
0!
#4410
b1 .
1!
#4420
0!
#4430
b10 .
1!
#4440
0!
#4450
b11 .
1!
#4460
0!
#4470
b0 .
1!
#4480
0!
#4490
b1 .
1!
#4500
0!
#4510
b10 .
1!
#4520
0!
#4530
b11 .
1!
#4540
0!
#4550
b0 .
1!
#4560
0!
#4570
b1 .
1!
#4580
0!
#4590
b10 .
1!
#4600
0!
#4610
b11 .
1!
#4620
0!
#4630
b0 .
1!
#4640
0!
#4650
b1 .
1!
#4660
0!
#4670
b10 .
1!
#4680
0!
#4690
b11 .
1!
#4700
0!
#4710
b0 .
1!
#4720
0!
#4730
b1 .
1!
#4740
0!
#4750
b10 .
1!
#4760
0!
#4770
b11 .
1!
#4780
0!
#4790
b0 .
1!
#4800
0!
#4810
b1 .
1!
#4820
0!
#4830
b10 .
1!
#4840
0!
#4850
b11 .
1!
#4860
0!
#4870
b0 .
1!
#4880
0!
#4890
b1 .
1!
#4900
0!
#4910
b10 .
1!
#4920
0!
#4930
b11 .
1!
#4940
0!
#4950
b0 .
1!
#4960
0!
#4970
b1 .
1!
#4980
0!
#4990
b10 .
1!
#5000
0!
#5010
b11 .
1!
#5020
0!
#5030
b0 .
1!
#5040
0!
#5050
b1 .
1!
#5060
0!
#5070
b10 .
1!
#5080
0!
#5090
b11 .
1!
#5100
0!
#5110
b0 .
1!
#5120
0!
#5130
b1 .
1!
#5140
0!
#5150
b10 .
1!
#5160
0!
#5170
b11 .
1!
#5180
0!
#5190
b0 .
1!
#5200
0!
#5210
b1 .
1!
#5220
0!
#5230
b10 .
1!
#5240
0!
#5250
b11 .
1!
#5260
0!
#5270
b0 .
1!
#5280
0!
#5290
b1 .
1!
#5300
0!
#5310
b10 .
1!
#5320
0!
#5330
b11 .
1!
#5340
0!
#5350
b0 .
1!
#5360
0!
#5370
b1 .
1!
#5380
0!
#5390
b10 .
1!
#5400
0!
#5410
b11 .
1!
#5420
0!
#5430
b0 .
1!
#5440
0!
#5450
b1 .
1!
#5460
0!
#5470
b10 .
1!
#5480
0!
#5490
b11 .
1!
#5500
0!
#5510
b0 .
1!
#5520
0!
#5530
b1 .
1!
#5540
0!
#5550
b10 .
1!
#5560
0!
#5570
b11 .
1!
#5580
0!
#5590
b0 .
1!
#5600
0!
#5610
b1 .
1!
#5620
0!
#5630
b10 .
1!
#5640
0!
#5650
b11 .
1!
#5660
0!
#5670
b0 .
1!
#5680
0!
#5690
b1 .
1!
#5700
0!
#5710
b10 .
1!
#5720
0!
#5730
b11 .
1!
#5740
0!
#5750
b0 .
1!
#5760
0!
#5770
b1 .
1!
#5780
0!
#5790
b10 .
1!
#5800
0!
#5810
b11 .
1!
#5820
0!
#5830
b0 .
1!
#5840
0!
#5850
b1 .
1!
#5860
0!
#5870
b10 .
1!
#5880
0!
#5890
b11 .
1!
#5900
0!
#5910
b0 .
1!
#5920
0!
#5930
b1 .
1!
#5940
0!
#5950
b10 .
1!
#5960
0!
#5970
b11 .
1!
#5980
0!
#5990
b0 .
1!
#6000
0!
#6010
b1 .
1!
#6020
0!
#6030
b10 .
1!
#6040
0!
#6050
b11 .
1!
#6060
0!
#6070
b0 .
1!
#6080
0!
#6090
b1 .
1!
#6100
0!
#6110
b10 .
1!
#6120
0!
#6130
b11 .
1!
#6140
0!
#6150
b0 .
1!
#6160
0!
#6170
b1 .
1!
#6180
0!
#6190
b10 .
1!
#6200
0!
#6210
b11 .
1!
#6220
0!
#6230
b0 .
1!
#6240
0!
#6250
b1 .
1!
#6260
0!
#6270
b10 .
1!
#6280
0!
#6290
b11 .
1!
#6300
0!
#6310
b0 .
1!
#6320
0!
#6330
b1 .
1!
#6340
0!
#6350
b10 .
1!
#6360
0!
#6370
b11 .
1!
#6380
0!
#6390
b0 .
1!
#6400
0!
#6410
b1 .
1!
#6420
0!
#6430
b10 .
1!
#6440
0!
#6450
b11 .
1!
#6460
0!
#6470
b0 .
1!
#6480
0!
#6490
b1 .
1!
#6500
0!
#6510
b10 .
1!
#6520
0!
#6530
b11 .
1!
#6540
0!
#6550
b0 .
1!
#6560
0!
#6570
b1 .
1!
#6580
0!
#6590
b10 .
1!
#6600
0!
#6610
b11 .
1!
#6620
0!
#6630
b0 .
1!
#6640
0!
#6650
b1 .
1!
#6660
0!
#6670
b10 .
1!
#6680
0!
#6690
b11 .
1!
#6700
0!
#6710
b0 .
1!
#6720
0!
#6730
b1 .
1!
#6740
0!
#6750
b10 .
1!
#6760
0!
#6770
b11 .
1!
#6780
0!
#6790
b0 .
1!
#6800
0!
#6810
b1 .
1!
#6820
0!
#6830
b10 .
1!
#6840
0!
#6850
b11 .
1!
#6860
0!
#6870
b0 .
1!
#6880
0!
#6890
b1 .
1!
#6900
0!
#6910
b10 .
1!
#6920
0!
#6930
b11 .
1!
#6940
0!
#6950
b0 .
1!
#6960
0!
#6970
b1 .
1!
#6980
0!
#6990
b10 .
1!
#7000
0!
#7010
b11 .
1!
#7020
0!
#7030
b0 .
1!
#7040
0!
#7050
b1 .
1!
#7060
0!
#7070
b10 .
1!
#7080
0!
#7090
b11 .
1!
#7100
0!
#7110
b0 .
1!
#7120
0!
#7130
b1 .
1!
#7140
0!
#7150
b10 .
1!
#7160
0!
#7170
b11 .
1!
#7180
0!
#7190
b0 .
1!
#7200
0!
#7210
b1 .
1!
#7220
0!
#7230
b10 .
1!
#7240
0!
#7250
b11 .
1!
#7260
0!
#7270
b0 .
1!
#7280
0!
#7290
b1 .
1!
#7300
0!
#7310
b10 .
1!
#7320
0!
#7330
b11 .
1!
#7340
0!
#7350
b0 .
1!
#7360
0!
#7370
b1 .
1!
#7380
0!
#7390
b10 .
1!
#7400
0!
#7410
b11 .
1!
#7420
0!
#7430
b0 .
1!
#7440
0!
#7450
b1 .
1!
#7460
0!
#7470
b10 .
1!
#7480
0!
#7490
b11 .
1!
#7500
0!
#7510
b0 .
1!
#7520
0!
#7530
b1 .
1!
#7540
0!
#7550
b10 .
1!
#7560
0!
#7570
b11 .
1!
#7580
0!
#7590
b0 .
1!
#7600
0!
#7610
b1 .
1!
#7620
0!
#7630
b10 .
1!
#7640
0!
#7650
b11 .
1!
#7660
0!
#7670
b0 .
1!
#7680
0!
#7690
b1 .
1!
#7700
0!
#7710
b10 .
1!
#7720
0!
#7730
b11 .
1!
#7740
0!
#7750
b0 .
1!
#7760
0!
#7770
b1 .
1!
#7780
0!
#7790
b10 .
1!
#7800
0!
#7810
b11 .
1!
#7820
0!
#7830
b0 .
1!
#7840
0!
#7850
b1 .
1!
#7860
0!
#7870
b10 .
1!
#7880
0!
#7890
b11 .
1!
#7900
0!
#7910
b0 .
1!
#7920
0!
#7930
b1 .
1!
#7940
0!
#7950
b10 .
1!
#7960
0!
#7970
b11 .
1!
#7980
0!
#7990
b0 .
1!
#8000
0!
#8010
b1 .
1!
#8020
0!
#8030
b10 .
1!
#8040
0!
#8050
b11 .
1!
#8060
0!
#8070
b0 .
1!
#8080
0!
#8090
b1 .
1!
#8100
0!
#8110
b10 .
1!
#8120
0!
#8130
b11 .
1!
#8140
0!
#8150
b0 .
1!
#8160
0!
#8170
b1 .
1!
#8180
0!
#8190
b10 .
1!
#8200
0!
#8210
b11 .
1!
#8220
0!
#8230
b0 .
1!
#8240
0!
#8250
b1 .
1!
#8260
0!
#8270
b10 .
1!
#8280
0!
#8290
b11 .
1!
#8300
0!
#8310
b0 .
1!
#8320
0!
#8330
b1 .
1!
#8340
0!
#8350
b10 .
1!
#8360
0!
#8370
b11 .
1!
#8380
0!
#8390
b0 .
1!
#8400
0!
#8410
b1 .
1!
#8420
0!
#8430
b10 .
1!
#8440
0!
#8450
b11 .
1!
#8460
0!
#8470
b0 .
1!
#8480
0!
#8490
b1 .
1!
#8500
0!
#8510
b10 .
1!
#8520
0!
#8530
b11 .
1!
#8540
0!
#8550
b0 .
1!
#8560
0!
#8570
b1 .
1!
#8580
0!
#8590
b10 .
1!
#8600
0!
#8610
b11 .
1!
#8620
0!
#8630
b0 .
1!
#8640
0!
#8650
b1 .
1!
#8660
0!
#8670
b10 .
1!
#8680
0!
#8690
b11 .
1!
#8700
0!
#8710
b0 .
1!
#8720
0!
#8730
b1 .
1!
#8740
0!
#8750
b10 .
1!
#8760
0!
#8770
b11 .
1!
#8780
0!
#8790
b0 .
1!
#8800
0!
#8810
b1 .
1!
#8820
0!
#8830
b10 .
1!
#8840
0!
#8850
b11 .
1!
#8860
0!
#8870
b0 .
1!
#8880
0!
#8890
b1 .
1!
#8900
0!
#8910
b10 .
1!
#8920
0!
#8930
b11 .
1!
#8940
0!
#8950
b0 .
1!
#8960
0!
#8970
b1 .
1!
#8980
0!
#8990
b10 .
1!
#9000
0!
#9010
b11 .
1!
#9020
0!
#9030
b0 .
1!
#9040
0!
#9050
b1 .
1!
#9060
0!
#9070
b10 .
1!
#9080
0!
#9090
b11 .
1!
#9100
0!
#9110
b0 .
1!
